main.py
rdjango/__init__.py
rdjango/example.py
RDjango-1.0.1.dist-info/LICENSE
RDjango-1.0.1.dist-info/METADATA
RDjango-1.0.1.dist-info/WHEEL
RDjango-1.0.1.dist-info/top_level.txt
RDjango-1.0.1.dist-info/RECORD
